README.md
__init__.py
src/__init__.py
src/convert_standard.py
src/decoder.py
src/default_processing.py
src/dumper.py
src/encoder.py
src/loader.py
src/parser.py
tests/__init__.py
tests/dump.json
tests/dumps.json
tests/sample.json
tests/test_dumper.py
tests/test_loader.py
json5rw-0.2.1.dist-info/WHEEL
json5rw-0.2.1.dist-info/METADATA
json5rw-0.2.1.dist-info/RECORD
