Metadata-Version: 2.1
Name: json5rw
Version: 0.2.1
Summary: A tool for JSON5 I/O
Author: Andy Zhang
Author-email: andy@nwsoft.tk
Requires-Python: >=3.10,<4.0
Classifier: Programming Language :: Python :: 3
Classifier: Programming Language :: Python :: 3.10
Classifier: Programming Language :: Python :: 3.11
